<?xml version="1.0"?>
<RuleSet xmlns:xsi="http://www.w3.org/2001/XMLSchema-instance" xmlns:xsd="http://www.w3.org/2001/XMLSchema">
  <rule>
    <ingredient>fire</ingredient>
    <ingredient>fire</ingredient>
  </rule>
  <rule>
    <ingredient>fire</ingredient>
    <ingredient>water</ingredient>
    <result>alcohol</result>
  </rule>
  <rule>
    <ingredient>earth</ingredient>
    <ingredient>fire</ingredient>
    <result>lava</result>
  </rule>
  <rule>
    <ingredient>air</ingredient>
    <ingredient>fire</ingredient>
    <result>energy</result>
  </rule>
  <rule>
    <ingredient>alcohol</ingredient>
    <ingredient>fire</ingredient>
    <result>molotov cocktail</result>
  </rule>
  <rule>
    <ingredient>fire</ingredient>
    <ingredient>lava</ingredient>
  </rule>
  <rule>
    <ingredient>energy</ingredient>
    <ingredient>fire</ingredient>
  </rule>
  <rule>
    <ingredient>fire</ingredient>
    <ingredient>molotov cocktail</ingredient>
  </rule>
  <rule>
    <ingredient>water</ingredient>
    <ingredient>water</ingredient>
  </rule>
  <rule>
    <ingredient>earth</ingredient>
    <ingredient>water</ingredient>
    <result>swamp</result>
  </rule>
  <rule>
    <ingredient>fire</ingredient>
    <ingredient>swamp</ingredient>
  </rule>
  <rule>
    <ingredient>air</ingredient>
    <ingredient>water</ingredient>
    <result>steam</result>
  </rule>
  <rule>
    <ingredient>fire</ingredient>
    <ingredient>steam</ingredient>
  </rule>
  <rule>
    <ingredient>alcohol</ingredient>
    <ingredient>water</ingredient>
    <result>vodka</result>
  </rule>
  <rule>
    <ingredient>fire</ingredient>
    <ingredient>vodka</ingredient>
  </rule>
  <rule>
    <ingredient>lava</ingredient>
    <ingredient>water</ingredient>
    <result>steam</result>
    <result>stone</result>
  </rule>
  <rule>
    <ingredient>fire</ingredient>
    <ingredient>stone</ingredient>
    <result>metal</result>
  </rule>
  <rule>
    <ingredient>fire</ingredient>
    <ingredient>metal</ingredient>
  </rule>
  <rule>
    <ingredient>energy</ingredient>
    <ingredient>water</ingredient>
  </rule>
  <rule>
    <ingredient>molotov cocktail</ingredient>
    <ingredient>water</ingredient>
  </rule>
  <rule>
    <ingredient>swamp</ingredient>
    <ingredient>water</ingredient>
  </rule>
  <rule>
    <ingredient>steam</ingredient>
    <ingredient>water</ingredient>
  </rule>
  <rule>
    <ingredient>vodka</ingredient>
    <ingredient>water</ingredient>
  </rule>
  <rule>
    <ingredient>stone</ingredient>
    <ingredient>water</ingredient>
    <result>sand</result>
  </rule>
  <rule>
    <ingredient>fire</ingredient>
    <ingredient>sand</ingredient>
    <result>glass</result>
  </rule>
  <rule>
    <ingredient>fire</ingredient>
    <ingredient>glass</ingredient>
    <result>lamp</result>
  </rule>
  <rule>
    <ingredient>fire</ingredient>
    <ingredient>lamp</ingredient>
  </rule>
  <rule>
    <ingredient>metal</ingredient>
    <ingredient>water</ingredient>
    <result>rust</result>
  </rule>
  <rule>
    <ingredient>fire</ingredient>
    <ingredient>rust</ingredient>
  </rule>
  <rule>
    <ingredient>sand</ingredient>
    <ingredient>water</ingredient>
    <result>beach</result>
  </rule>
  <rule>
    <ingredient>beach</ingredient>
    <ingredient>fire</ingredient>
  </rule>
  <rule>
    <ingredient>glass</ingredient>
    <ingredient>water</ingredient>
    <result>ice</result>
  </rule>
  <rule>
    <ingredient>fire</ingredient>
    <ingredient>ice</ingredient>
    <result>water</result>
  </rule>
  <rule>
    <ingredient>lamp</ingredient>
    <ingredient>water</ingredient>
  </rule>
  <rule>
    <ingredient>rust</ingredient>
    <ingredient>water</ingredient>
  </rule>
  <rule>
    <ingredient>beach</ingredient>
    <ingredient>water</ingredient>
  </rule>
  <rule>
    <ingredient>ice</ingredient>
    <ingredient>water</ingredient>
  </rule>
  <rule>
    <ingredient>earth</ingredient>
    <ingredient>earth</ingredient>
    <result>pressure</result>
  </rule>
  <rule>
    <ingredient>fire</ingredient>
    <ingredient>pressure</ingredient>
  </rule>
  <rule>
    <ingredient>pressure</ingredient>
    <ingredient>water</ingredient>
  </rule>
  <rule>
    <ingredient>air</ingredient>
    <ingredient>earth</ingredient>
    <result>dust</result>
  </rule>
  <rule>
    <ingredient>dust</ingredient>
    <ingredient>fire</ingredient>
    <result>gunpowder</result>
  </rule>
  <rule>
    <ingredient>fire</ingredient>
    <ingredient>gunpowder</ingredient>
    <result>smoke</result>
    <result>explosion</result>
  </rule>
  <rule>
    <ingredient>fire</ingredient>
    <ingredient>smoke</ingredient>
  </rule>
  <rule>
    <ingredient>explosion</ingredient>
    <ingredient>fire</ingredient>
  </rule>
  <rule>
    <ingredient>dust</ingredient>
    <ingredient>water</ingredient>
    <result>mud</result>
  </rule>
  <rule>
    <ingredient>fire</ingredient>
    <ingredient>mud</ingredient>
  </rule>
  <rule>
    <ingredient>gunpowder</ingredient>
    <ingredient>water</ingredient>
  </rule>
  <rule>
    <ingredient>smoke</ingredient>
    <ingredient>water</ingredient>
  </rule>
  <rule>
    <ingredient>explosion</ingredient>
    <ingredient>water</ingredient>
  </rule>
  <rule>
    <ingredient>mud</ingredient>
    <ingredient>water</ingredient>
  </rule>
  <rule>
    <ingredient>alcohol</ingredient>
    <ingredient>earth</ingredient>
  </rule>
  <rule>
    <ingredient>earth</ingredient>
    <ingredient>lava</ingredient>
  </rule>
  <rule>
    <ingredient>earth</ingredient>
    <ingredient>energy</ingredient>
  </rule>
  <rule>
    <ingredient>earth</ingredient>
    <ingredient>molotov cocktail</ingredient>
  </rule>
  <rule>
    <ingredient>earth</ingredient>
    <ingredient>swamp</ingredient>
  </rule>
  <rule>
    <ingredient>earth</ingredient>
    <ingredient>steam</ingredient>
    <result>geyser</result>
  </rule>
  <rule>
    <ingredient>fire</ingredient>
    <ingredient>geyser</ingredient>
  </rule>
  <rule>
    <ingredient>geyser</ingredient>
    <ingredient>water</ingredient>
  </rule>
  <rule>
    <ingredient>earth</ingredient>
    <ingredient>vodka</ingredient>
  </rule>
  <rule>
    <ingredient>earth</ingredient>
    <ingredient>stone</ingredient>
  </rule>
  <rule>
    <ingredient>earth</ingredient>
    <ingredient>metal</ingredient>
  </rule>
  <rule>
    <ingredient>earth</ingredient>
    <ingredient>sand</ingredient>
  </rule>
  <rule>
    <ingredient>earth</ingredient>
    <ingredient>glass</ingredient>
  </rule>
  <rule>
    <ingredient>earth</ingredient>
    <ingredient>lamp</ingredient>
  </rule>
  <rule>
    <ingredient>earth</ingredient>
    <ingredient>rust</ingredient>
  </rule>
  <rule>
    <ingredient>beach</ingredient>
    <ingredient>earth</ingredient>
  </rule>
  <rule>
    <ingredient>earth</ingredient>
    <ingredient>ice</ingredient>
  </rule>
  <rule>
    <ingredient>earth</ingredient>
    <ingredient>pressure</ingredient>
  </rule>
  <rule>
    <ingredient>dust</ingredient>
    <ingredient>earth</ingredient>
  </rule>
  <rule>
    <ingredient>earth</ingredient>
    <ingredient>gunpowder</ingredient>
  </rule>
  <rule>
    <ingredient>earth</ingredient>
    <ingredient>smoke</ingredient>
  </rule>
  <rule>
    <ingredient>earth</ingredient>
    <ingredient>explosion</ingredient>
  </rule>
  <rule>
    <ingredient>earth</ingredient>
    <ingredient>mud</ingredient>
  </rule>
  <rule>
    <ingredient>earth</ingredient>
    <ingredient>geyser</ingredient>
  </rule>
  <rule>
    <ingredient>air</ingredient>
    <ingredient>air</ingredient>
    <result>wind</result>
  </rule>
  <rule>
    <ingredient>fire</ingredient>
    <ingredient>wind</ingredient>
  </rule>
  <rule>
    <ingredient>water</ingredient>
    <ingredient>wind</ingredient>
  </rule>
  <rule>
    <ingredient>earth</ingredient>
    <ingredient>wind</ingredient>
  </rule>
  <rule>
    <ingredient>air</ingredient>
    <ingredient>alcohol</ingredient>
  </rule>
  <rule>
    <ingredient>air</ingredient>
    <ingredient>lava</ingredient>
    <result>stone</result>
  </rule>
  <rule>
    <ingredient>air</ingredient>
    <ingredient>energy</ingredient>
    <result>storm</result>
  </rule>
  <rule>
    <ingredient>fire</ingredient>
    <ingredient>storm</ingredient>
  </rule>
  <rule>
    <ingredient>storm</ingredient>
    <ingredient>water</ingredient>
    <result>typhoon</result>
  </rule>
  <rule>
    <ingredient>fire</ingredient>
    <ingredient>typhoon</ingredient>
  </rule>
  <rule>
    <ingredient>typhoon</ingredient>
    <ingredient>water</ingredient>
  </rule>
  <rule>
    <ingredient>earth</ingredient>
    <ingredient>storm</ingredient>
  </rule>
  <rule>
    <ingredient>earth</ingredient>
    <ingredient>typhoon</ingredient>
  </rule>
  <rule>
    <ingredient>air</ingredient>
    <ingredient>molotov cocktail</ingredient>
  </rule>
  <rule>
    <ingredient>air</ingredient>
    <ingredient>swamp</ingredient>
  </rule>
  <rule>
    <ingredient>air</ingredient>
    <ingredient>steam</ingredient>
    <result>cloud</result>
  </rule>
  <rule>
    <ingredient>cloud</ingredient>
    <ingredient>fire</ingredient>
  </rule>
  <rule>
    <ingredient>cloud</ingredient>
    <ingredient>water</ingredient>
  </rule>
  <rule>
    <ingredient>cloud</ingredient>
    <ingredient>earth</ingredient>
  </rule>
  <rule>
    <ingredient>air</ingredient>
    <ingredient>vodka</ingredient>
  </rule>
  <rule>
    <ingredient>air</ingredient>
    <ingredient>stone</ingredient>
    <result>sand</result>
  </rule>
  <rule>
    <ingredient>air</ingredient>
    <ingredient>metal</ingredient>
  </rule>
  <rule>
    <ingredient>air</ingredient>
    <ingredient>sand</ingredient>
  </rule>
  <rule>
    <ingredient>air</ingredient>
    <ingredient>glass</ingredient>
  </rule>
  <rule>
    <ingredient>air</ingredient>
    <ingredient>lamp</ingredient>
  </rule>
  <rule>
    <ingredient>air</ingredient>
    <ingredient>rust</ingredient>
  </rule>
  <rule>
    <ingredient>air</ingredient>
    <ingredient>beach</ingredient>
  </rule>
  <rule>
    <ingredient>air</ingredient>
    <ingredient>ice</ingredient>
  </rule>
  <rule>
    <ingredient>air</ingredient>
    <ingredient>pressure</ingredient>
  </rule>
  <rule>
    <ingredient>air</ingredient>
    <ingredient>dust</ingredient>
  </rule>
  <rule>
    <ingredient>air</ingredient>
    <ingredient>gunpowder</ingredient>
  </rule>
  <rule>
    <ingredient>air</ingredient>
    <ingredient>smoke</ingredient>
  </rule>
  <rule>
    <ingredient>air</ingredient>
    <ingredient>explosion</ingredient>
  </rule>
  <rule>
    <ingredient>air</ingredient>
    <ingredient>mud</ingredient>
  </rule>
  <rule>
    <ingredient>air</ingredient>
    <ingredient>geyser</ingredient>
  </rule>
  <rule>
    <ingredient>air</ingredient>
    <ingredient>wind</ingredient>
  </rule>
  <rule>
    <ingredient>air</ingredient>
    <ingredient>storm</ingredient>
  </rule>
  <rule>
    <ingredient>air</ingredient>
    <ingredient>typhoon</ingredient>
  </rule>
  <rule>
    <ingredient>air</ingredient>
    <ingredient>cloud</ingredient>
    <result>sky</result>
  </rule>
  <rule>
    <ingredient>fire</ingredient>
    <ingredient>sky</ingredient>
  </rule>
  <rule>
    <ingredient>sky</ingredient>
    <ingredient>water</ingredient>
  </rule>
  <rule>
    <ingredient>earth</ingredient>
    <ingredient>sky</ingredient>
  </rule>
  <rule>
    <ingredient>air</ingredient>
    <ingredient>sky</ingredient>
  </rule>
  <rule>
    <ingredient>alcohol</ingredient>
    <ingredient>alcohol</ingredient>
  </rule>
  <rule>
    <ingredient>alcohol</ingredient>
    <ingredient>lava</ingredient>
  </rule>
  <rule>
    <ingredient>alcohol</ingredient>
    <ingredient>energy</ingredient>
  </rule>
  <rule>
    <ingredient>alcohol</ingredient>
    <ingredient>molotov cocktail</ingredient>
  </rule>
  <rule>
    <ingredient>alcohol</ingredient>
    <ingredient>swamp</ingredient>
  </rule>
  <rule>
    <ingredient>alcohol</ingredient>
    <ingredient>steam</ingredient>
  </rule>
  <rule>
    <ingredient>alcohol</ingredient>
    <ingredient>vodka</ingredient>
  </rule>
  <rule>
    <ingredient>alcohol</ingredient>
    <ingredient>stone</ingredient>
  </rule>
  <rule>
    <ingredient>alcohol</ingredient>
    <ingredient>metal</ingredient>
  </rule>
  <rule>
    <ingredient>alcohol</ingredient>
    <ingredient>sand</ingredient>
  </rule>
  <rule>
    <ingredient>alcohol</ingredient>
    <ingredient>glass</ingredient>
  </rule>
  <rule>
    <ingredient>alcohol</ingredient>
    <ingredient>lamp</ingredient>
  </rule>
  <rule>
    <ingredient>alcohol</ingredient>
    <ingredient>rust</ingredient>
  </rule>
  <rule>
    <ingredient>alcohol</ingredient>
    <ingredient>beach</ingredient>
  </rule>
  <rule>
    <ingredient>alcohol</ingredient>
    <ingredient>ice</ingredient>
  </rule>
  <rule>
    <ingredient>alcohol</ingredient>
    <ingredient>pressure</ingredient>
  </rule>
  <rule>
    <ingredient>alcohol</ingredient>
    <ingredient>dust</ingredient>
  </rule>
  <rule>
    <ingredient>alcohol</ingredient>
    <ingredient>gunpowder</ingredient>
  </rule>
  <rule>
    <ingredient>alcohol</ingredient>
    <ingredient>smoke</ingredient>
  </rule>
  <rule>
    <ingredient>alcohol</ingredient>
    <ingredient>explosion</ingredient>
  </rule>
  <rule>
    <ingredient>alcohol</ingredient>
    <ingredient>mud</ingredient>
  </rule>
  <rule>
    <ingredient>alcohol</ingredient>
    <ingredient>geyser</ingredient>
  </rule>
  <rule>
    <ingredient>alcohol</ingredient>
    <ingredient>wind</ingredient>
  </rule>
  <rule>
    <ingredient>alcohol</ingredient>
    <ingredient>storm</ingredient>
  </rule>
  <rule>
    <ingredient>alcohol</ingredient>
    <ingredient>typhoon</ingredient>
  </rule>
  <rule>
    <ingredient>alcohol</ingredient>
    <ingredient>cloud</ingredient>
  </rule>
  <rule>
    <ingredient>alcohol</ingredient>
    <ingredient>sky</ingredient>
  </rule>
  <rule>
    <ingredient>lava</ingredient>
    <ingredient>lava</ingredient>
  </rule>
  <rule>
    <ingredient>energy</ingredient>
    <ingredient>lava</ingredient>
  </rule>
  <rule>
    <ingredient>lava</ingredient>
    <ingredient>molotov cocktail</ingredient>
  </rule>
  <rule>
    <ingredient>lava</ingredient>
    <ingredient>swamp</ingredient>
  </rule>
  <rule>
    <ingredient>lava</ingredient>
    <ingredient>steam</ingredient>
  </rule>
  <rule>
    <ingredient>lava</ingredient>
    <ingredient>vodka</ingredient>
  </rule>
  <rule>
    <ingredient>lava</ingredient>
    <ingredient>stone</ingredient>
  </rule>
  <rule>
    <ingredient>lava</ingredient>
    <ingredient>metal</ingredient>
  </rule>
  <rule>
    <ingredient>lava</ingredient>
    <ingredient>sand</ingredient>
  </rule>
  <rule>
    <ingredient>glass</ingredient>
    <ingredient>lava</ingredient>
  </rule>
  <rule>
    <ingredient>lamp</ingredient>
    <ingredient>lava</ingredient>
    <result>lavalamp</result>
  </rule>
  <rule>
    <ingredient>fire</ingredient>
    <ingredient>lavalamp</ingredient>
  </rule>
  <rule>
    <ingredient>lavalamp</ingredient>
    <ingredient>water</ingredient>
  </rule>
  <rule>
    <ingredient>earth</ingredient>
    <ingredient>lavalamp</ingredient>
  </rule>
  <rule>
    <ingredient>air</ingredient>
    <ingredient>lavalamp</ingredient>
  </rule>
  <rule>
    <ingredient>alcohol</ingredient>
    <ingredient>lavalamp</ingredient>
  </rule>
  <rule>
    <ingredient>lava</ingredient>
    <ingredient>rust</ingredient>
  </rule>
  <element>fire</element>
  <element>water</element>
  <element>earth</element>
  <element>air</element>
  <element>alcohol</element>
  <element>lava</element>
  <element>energy</element>
  <element>molotov cocktail</element>
  <element>swamp</element>
  <element>steam</element>
  <element>vodka</element>
  <element>stone</element>
  <element>metal</element>
  <element>sand</element>
  <element>glass</element>
  <element>lamp</element>
  <element>rust</element>
  <element>beach</element>
  <element>ice</element>
  <element>pressure</element>
  <element>dust</element>
  <element>gunpowder</element>
  <element>smoke</element>
  <element>explosion</element>
  <element>mud</element>
  <element>geyser</element>
  <element>wind</element>
  <element>storm</element>
  <element>typhoon</element>
  <element>cloud</element>
  <element>sky</element>
  <element>lavalamp</element>
</RuleSet>